chaos_basispy/_AS_adaptation.py
chaos_basispy/__init__.py
chaos_basispy/_basis_adaptation.py
chaos_basispy/_poly_basis.py
chaos_basispy/_poly_chaos.py
chaos_basispy/_quadrature.py
chaos_basispy/_sparse_grid.py
chaos_basispy/_tools.py
chaos_basispy-0.2.1.dist-info/LICENSE
chaos_basispy-0.2.1.dist-info/METADATA
chaos_basispy-0.2.1.dist-info/WHEEL
chaos_basispy-0.2.1.dist-info/top_level.txt
chaos_basispy-0.2.1.dist-info/RECORD
