Metadata-Version: 2.1
Name: chaos-basispy
Version: 0.2.1
Summary: A package for Polynomial Chaos basis rotation
Home-page: https://github.com/tsilifis/chaos_basispy
Author: Panagiotis Tsilifis
Author-email: panagiotis.tsilifis@epfl.ch
License: UNKNOWN
Keywords: polynomial chaos,hermite chaos,legendre_chaos,dimensionality reduction,surrogate,uncertainty quantification
Platform: UNKNOWN
